langchain_mistralai/__init__.py
langchain_mistralai/_compat.py
langchain_mistralai/chat_models.py
langchain_mistralai/embeddings.py
langchain_mistralai/py.typed
langchain_mistralai-1.0.0.dist-info/METADATA
langchain_mistralai-1.0.0.dist-info/WHEEL
langchain_mistralai-1.0.0.dist-info/licenses/LICENSE
langchain_mistralai-1.0.0.dist-info/RECORD
