Metadata-Version: 2.4
Name: langchain-mistralai
Version: 1.0.0
Summary: An integration package connecting Mistral and LangChain
Project-URL: homepage, https://docs.langchain.com/oss/python/integrations/providers/mistralai
Project-URL: repository, https://github.com/langchain-ai/langchain/tree/master/libs/partners/mistralai
Project-URL: changelog, https://github.com/langchain-ai/langchain/releases?q=%22langchain-mistralai%22
Project-URL: docs, https://reference.langchain.com/python/integrations/langchain_mistralai/
Project-URL: twitter, https://x.com/LangChainAI
Project-URL: slack, https://www.langchain.com/join-community
Project-URL: reddit, https://www.reddit.com/r/LangChain/
License: MIT
License-File: LICENSE
Requires-Python: <4.0.0,>=3.10.0
Requires-Dist: httpx-sse<1.0.0,>=0.3.1
Requires-Dist: httpx<1.0.0,>=0.25.2
Requires-Dist: langchain-core<2.0.0,>=1.0.0
Requires-Dist: pydantic<3.0.0,>=2.0.0
Requires-Dist: tokenizers<1.0.0,>=0.15.1
